argparse_subdec/__init__.py
argparse_subdec/py.typed
argparse_subdec/subdec.py
argparse_subdec-0.2.1.dist-info/LICENSE.txt
argparse_subdec-0.2.1.dist-info/METADATA
argparse_subdec-0.2.1.dist-info/WHEEL
argparse_subdec-0.2.1.dist-info/top_level.txt
argparse_subdec-0.2.1.dist-info/RECORD
