Metadata-Version: 2.1
Name: argparse-subdec
Version: 0.2.1
Summary: UNKNOWN
Home-page: https://github.com/guludo/python-argparse-subdec
License: UNKNOWN
Platform: UNKNOWN
Classifier: Development Status :: 4 - Beta
Classifier: Intended Audience :: Developers
Classifier: License :: OSI Approved :: Mozilla Public License 2.0 (MPL 2.0)
Classifier: Programming Language :: Python :: 3
License-File: LICENSE.txt
Provides-Extra: all
Requires-Dist: pytest (~=6.2) ; extra == 'all'
Requires-Dist: coverage (~=5.5) ; extra == 'all'
Requires-Dist: mypy (>=0.910<1) ; extra == 'all'
Provides-Extra: dev
Requires-Dist: pytest (~=6.2) ; extra == 'dev'
Requires-Dist: coverage (~=5.5) ; extra == 'dev'
Requires-Dist: mypy (>=0.910<1) ; extra == 'dev'
Provides-Extra: tests
Requires-Dist: pytest (~=6.2) ; extra == 'tests'
Requires-Dist: coverage (~=5.5) ; extra == 'tests'
